README.rst
setup.py
elasticbox/__init__.py
elasticbox/box.py
elasticbox/context.py
elasticbox/entrypoint.py
elasticbox/instance.py
elasticbox/session.py
elasticbox/template.py
elasticbox/commands/__init__.py
elasticbox/commands/config.py
elasticbox/commands/run.py
elasticbox/commands/set.py
elasticbox/commands/setup.py
elasticbox_docker.egg-info/PKG-INFO
elasticbox_docker.egg-info/SOURCES.txt
elasticbox_docker.egg-info/dependency_links.txt
elasticbox_docker.egg-info/entry_points.txt
elasticbox_docker.egg-info/requires.txt
elasticbox_docker.egg-info/top_level.txt