Metadata-Version: 1.1
Name: elasticbox-docker
Version: 1.0.4
Summary: API Client library for ElasticBox
Home-page: https://elasticbox.com
Author: ElasticBox Inc
Author-email: operations@elasticbox.com
License: Apache License 2.0
Platform: UNKNOWN
Classifier: Intended Audience :: Developers
Classifier: Intended Audience :: System Administrators
Classifier: Natural Language :: English
Classifier: License :: OSI Approved :: Apache Software License
Classifier: Programming Language :: Python
Classifier: Programming Language :: Python :: 2.7
